corkus/__init__.py
corkus/client.py
corkus/errors.py
corkus/py.typed
corkus/version.py
corkus/data/__init__.py
corkus/data/ids_convert.py
corkus/data/major_ids.py
corkus/endpoints/__init__.py
corkus/endpoints/endpoint.py
corkus/endpoints/guild.py
corkus/endpoints/ingredient.py
corkus/endpoints/item.py
corkus/endpoints/leaderboard.py
corkus/endpoints/network.py
corkus/endpoints/player.py
corkus/endpoints/recipe.py
corkus/endpoints/search.py
corkus/endpoints/territory.py
corkus/objects/__init__.py
corkus/objects/armour_defense.py
corkus/objects/base.py
corkus/objects/base_guild.py
corkus/objects/base_partial_member.py
corkus/objects/base_player.py
corkus/objects/base_server.py
corkus/objects/color.py
corkus/objects/dungeon.py
corkus/objects/enums.py
corkus/objects/guild.py
corkus/objects/guild_banner.py
corkus/objects/identification.py
corkus/objects/identification_type.py
corkus/objects/identification_values.py
corkus/objects/ingredient.py
corkus/objects/ingredient_comsumable.py
corkus/objects/ingredient_item.py
corkus/objects/ingredient_position.py
corkus/objects/ingredient_sprite.py
corkus/objects/item.py
corkus/objects/leaderboard_guild.py
corkus/objects/leaderboard_partial_member.py
corkus/objects/leaderboard_player.py
corkus/objects/level_range.py
corkus/objects/major_identification.py
corkus/objects/material.py
corkus/objects/member.py
corkus/objects/mojang_skin_response.py
corkus/objects/online_players.py
corkus/objects/partial_base.py
corkus/objects/partial_guild.py
corkus/objects/partial_ingredient.py
corkus/objects/partial_member.py
corkus/objects/partial_online_player.py
corkus/objects/partial_player.py
corkus/objects/partial_recipe.py
corkus/objects/partial_server.py
corkus/objects/partial_teritories.py
corkus/objects/player.py
corkus/objects/player_character.py
corkus/objects/player_gamemodes.py
corkus/objects/player_profession.py
corkus/objects/player_ranking.py
corkus/objects/player_statistics.py
corkus/objects/player_status.py
corkus.py-3.1.0.dist-info/LICENSE
corkus.py-3.1.0.dist-info/METADATA
corkus.py-3.1.0.dist-info/WHEEL
corkus.py-3.1.0.dist-info/top_level.txt
corkus.py-3.1.0.dist-info/RECORD
