Metadata-Version: 2.1
Name: corkus.py
Version: 3.1.0
Summary: Asynchronous, feature-rich and easy to use Python wrapper for Public Wynncraft API
Home-page: https://github.com/MrBartusek/corkus.py
Author: MrBartusek
License: MIT
Project-URL: Documentation, https://corkuspy.readthedocs.io/en/stable/
Project-URL: Issue tracker, https://github.com/MrBartusek/corkus.py/issues
Classifier: Development Status :: 7 - Inactive
Classifier: License :: OSI Approved :: MIT License
Classifier: Intended Audience :: Developers
Classifier: Natural Language :: English
Classifier: Operating System :: OS Independent
Classifier: Programming Language :: Python :: 3
Classifier: Programming Language :: Python :: 3.8
Classifier: Programming Language :: Python :: 3.9
Classifier: Programming Language :: Python :: 3.10
Classifier: Programming Language :: Python :: 3.11
Classifier: Topic :: Internet
Classifier: Topic :: Games/Entertainment
Classifier: Topic :: Software Development :: Libraries
Classifier: Topic :: Software Development :: Libraries :: Python Modules
Classifier: Topic :: Utilities
Requires-Python: >=3.8.0
License-File: LICENSE
Requires-Dist: aiohttp >=3.9.0
Requires-Dist: iso8601 <1.2.0,>=0.1.10
Requires-Dist: Deprecated <1.3.0,>=1.2.0
